[{"Year":null,"Value":null,"UNIT_MEASURE":null,"SERIES":null},{"Year":null,"Value":null,"UNIT_MEASURE":null,"SERIES":null},{"Year":null,"Value":null,"UNIT_MEASURE":null,"SERIES":null},{"Year":null,"Value":null,"UNIT_MEASURE":null,"SERIES":null},{"Year":null,"Value":null,"UNIT_MEASURE":null,"SERIES":null},{"Year":null,"Value":null,"UNIT_MEASURE":null,"SERIES":null},{"Year":null,"Value":null,"UNIT_MEASURE":null,"SERIES":null},{"Year":null,"Value":null,"UNIT_MEASURE":null,"SERIES":null},{"Year":null,"Value":null,"UNIT_MEASURE":null,"SERIES":null},{"Year":null,"Value":null,"UNIT_MEASURE":null,"SERIES":null},{"Year":null,"Value":null,"UNIT_MEASURE":null,"SERIES":null},{"Year":null,"Value":null,"UNIT_MEASURE":null,"SERIES":null},{"Year":null,"Value":null,"UNIT_MEASURE":null,"SERIES":null},{"Year":null,"Value":null,"UNIT_MEASURE":null,"SERIES":null},{"Year":null,"Value":null,"UNIT_MEASURE":null,"SERIES":null},{"Year":null,"Value":null,"UNIT_MEASURE":null,"SERIES":null},{"Year":null,"Value":null,"UNIT_MEASURE":null,"SERIES":null},{"Year":null,"Value":null,"UNIT_MEASURE":null,"SERIES":null},{"Year":null,"Value":null,"UNIT_MEASURE":null,"SERIES":null},{"Year":null,"Value":null,"UNIT_MEASURE":null,"SERIES":null},{"Year":null,"Value":null,"UNIT_MEASURE":null,"SERIES":null},{"Year":null,"Value":null,"UNIT_MEASURE":null,"SERIES":null},{"Year":null,"Value":null,"UNIT_MEASURE":null,"SERIES":null},{"Year":null,"Value":null,"UNIT_MEASURE":null,"SERIES":null},{"Year":null,"Value":null,"UNIT_MEASURE":null,"SERIES":null},{"Year":null,"Value":null,"UNIT_MEASURE":null,"SERIES":null},{"Year":null,"Value":null,"UNIT_MEASURE":null,"SERIES":null},{"Year":null,"Value":null,"UNIT_MEASURE":null,"SERIES":null},{"Year":null,"Value":null,"UNIT_MEASURE":null,"SERIES":null},{"Year":null,"Value":null,"UNIT_MEASURE":null,"SERIES":null},{"Year":null,"Value":null,"UNIT_MEASURE":null,"SERIES":null},{"Year":null,"Value":null,"UNIT_MEASURE":null,"SERIES":null},{"Year":null,"Value":null,"UNIT_MEASURE":null,"SERIES":null},{"Year":null,"Value":null,"UNIT_MEASURE":null,"SERIES":null},{"Year":null,"Value":null,"UNIT_MEASURE":null,"SERIES":null},{"Year":null,"Value":null,"UNIT_MEASURE":null,"SERIES":null},{"Year":null,"Value":null,"UNIT_MEASURE":null,"SERIES":null},{"Year":null,"Value":null,"UNIT_MEASURE":null,"SERIES":null},{"Year":null,"Value":null,"UNIT_MEASURE":null,"SERIES":null},{"Year":null,"Value":null,"UNIT_MEASURE":null,"SERIES":null},{"Year":null,"Value":null,"UNIT_MEASURE":null,"SERIES":null},{"Year":null,"Value":null,"UNIT_MEASURE":null,"SERIES":null},{"Year":null,"Value":null,"UNIT_MEASURE":null,"SERIES":null},{"Year":null,"Value":null,"UNIT_MEASURE":null,"SERIES":null},{"Year":null,"Value":null,"UNIT_MEASURE":null,"SERIES":null},{"Year":null,"Value":null,"UNIT_MEASURE":null,"SERIES":null},{"Year":null,"Value":null,"UNIT_MEASURE":null,"SERIES":null},{"Year":null,"Value":null,"UNIT_MEASURE":null,"SERIES":null},{"Year":null,"Value":null,"UNIT_MEASURE":null,"SERIES":null},{"Year":null,"Value":null,"UNIT_MEASURE":null,"SERIES":null},{"Year":null,"Value":null,"UNIT_MEASURE":null,"SERIES":null},{"Year":null,"Value":null,"UNIT_MEASURE":null,"SERIES":null},{"Year":null,"Value":null,"UNIT_MEASURE":null,"SERIES":null},{"Year":null,"Value":null,"UNIT_MEASURE":null,"SERIES":null},{"Year":null,"Value":null,"UNIT_MEASURE":null,"SERIES":null},{"Year":null,"Value":null,"UNIT_MEASURE":null,"SERIES":null},{"Year":null,"Value":null,"UNIT_MEASURE":null,"SERIES":null},{"Year":null,"Value":null,"UNIT_MEASURE":null,"SERIES":null},{"Year":null,"Value":null,"UNIT_MEASURE":null,"SERIES":null},{"Year":null,"Value":null,"UNIT_MEASURE":null,"SERIES":null},{"Year":null,"Value":null,"UNIT_MEASURE":null,"SERIES":null},{"Year":null,"Value":null,"UNIT_MEASURE":null,"SERIES":null},{"Year":null,"Value":null,"UNIT_MEASURE":null,"SERIES":null},{"Year":null,"Value":null,"UNIT_MEASURE":null,"SERIES":null},{"Year":null,"Value":null,"UNIT_MEASURE":null,"SERIES":null},{"Year":2020.0,"Value":0.01065,"UNIT_MEASURE":"PT","SERIES":"TX_IMP_GBSVR"},{"Year":2021.0,"Value":0.01232,"UNIT_MEASURE":"PT","SERIES":"TX_IMP_GBSVR"}]