{"Year":["2011-2012","2011-2012","2011-2012","2011-2012","2011-2012",null],"SERIES":["SE_DEV_ONTRK36-59","SE_DEV_ONTRK36-59","SE_DEV_ONTRK36-59","SE_DEV_ONTRK36-59","SE_DEV_ONTRK36-59",null],"UNIT_MEASURE":["Percent","Percent","Percent","Percent","Percent",null],"COMPOSITE_BREAKDOWN":["early_childhood_dev_ind","literacy","p_dev","soc_dev","learning",null],"Sex":["Both sexes or no breakdown by sex","Both sexes or no breakdown by sex","Both sexes or no breakdown by sex","Both sexes or no breakdown by sex","Both sexes or no breakdown by sex",null],"Value":[95.6,26.7,99.5,93.9,99.1,null]}